LICENSE
MANIFEST.in
README.md
setup.py
django_macros.egg-info/PKG-INFO
django_macros.egg-info/SOURCES.txt
django_macros.egg-info/dependency_links.txt
django_macros.egg-info/requires.txt
django_macros.egg-info/top_level.txt
macros/__init__.py
macros/tests.py
macros/templates/macros/tests/testmacros.html
macros/templatetags/__init__.py
macros/templatetags/macros.py
macros/templatetags/repeatedblocks.py