Metadata-Version: 1.1
Name: django-macros
Version: 0.3.1
Summary: A Django template tag library for repeating blocks tags and creating in template macros.
Home-page: https://github.com/nalourie/django-macros
Author: Nick Lourie
Author-email: developer.nick@kozbox.com
License: MIT License
Keywords: django repeat macros macro templatetags
Platform: UNKNOWN
Classifier: Environment :: Web Environment
Classifier: Framework :: Django
Classifier: Intended Audience :: Developers
Classifier: License :: OSI Approved :: MIT License
Classifier: Operating System :: OS Independent
Classifier: Programming Language :: Python
Classifier: Programming Language :: Python :: 2.7
Classifier: Programming Language :: Python :: 3
Classifier: Programming Language :: Python :: 3.4
Classifier: Topic :: Internet :: WWW/HTTP
Classifier: Topic :: Internet :: WWW/HTTP :: Dynamic Content
